modeling_gui/__init__.py
modeling_gui/dialogs.py
modeling_gui/main.py
modeling_gui/models.py
modeling_gui/visualization.py
modeling_gui/data/sample_data.csv
modeling_gui/utils/__init__.py
modeling_gui/utils/data_preprocessing.py
modeling_gui/utils/file_helper.py
tests/__init__.py
tests/test_models.py
modeling_gui-0.1.1.dist-info/LICENSE
modeling_gui-0.1.1.dist-info/METADATA
modeling_gui-0.1.1.dist-info/WHEEL
modeling_gui-0.1.1.dist-info/entry_points.txt
modeling_gui-0.1.1.dist-info/top_level.txt
modeling_gui-0.1.1.dist-info/RECORD
