Metadata-Version: 2.1
Name: modeling_gui
Version: 0.1.1
Summary: A PyQt5-based GUI for running statistical and machine learning models with customizable parameters and visualizations.
Home-page: https://github.com/your_username/modeling_gui
Author: Chandrasekar SUBRAMANI NARAYANA
Author-email: chandrasekarnarayana@gmail.com
Classifier: Programming Language :: Python :: 3
Classifier: License :: OSI Approved :: GNU General Public License v3 (GPLv3)
Classifier: Operating System :: OS Independent
Requires-Python: >=3.9
License-File: LICENSE
Requires-Dist: pyqt5 >=5.15.4
Requires-Dist: matplotlib >=3.4.3
Requires-Dist: seaborn >=0.11.2
Requires-Dist: pandas >=1.3.3
Requires-Dist: statsmodels >=0.12.2
Requires-Dist: scikit-learn >=0.24.2
Requires-Dist: scipy >=1.7.1
Requires-Dist: graphviz >=0.16
Requires-Dist: numpy >=1.21.2
